MANIFEST.in
knowledge_demo.xml
knowledge_view.xml
res_config_view.xml
setup.py
./__init__.py
./__openerp__.py
./res_config.py
i18n/ar.po
i18n/bg.po
i18n/ca.po
i18n/cs.po
i18n/da.po
i18n/de.po
i18n/en_GB.po
i18n/es.po
i18n/es_AR.po
i18n/es_CR.po
i18n/es_MX.po
i18n/es_VE.po
i18n/et.po
i18n/fi.po
i18n/fr.po
i18n/gl.po
i18n/hi.po
i18n/hr.po
i18n/hu.po
i18n/it.po
i18n/ja.po
i18n/knowledge.pot
i18n/lo.po
i18n/lv.po
i18n/mk.po
i18n/mn.po
i18n/nb.po
i18n/nl.po
i18n/nl_BE.po
i18n/pl.po
i18n/pt.po
i18n/pt_BR.po
i18n/ro.po
i18n/ru.po
i18n/sk.po
i18n/sl.po
i18n/sr.po
i18n/sr@latin.po
i18n/sv.po
i18n/th.po
i18n/tr.po
i18n/zh_CN.po
i18n/zh_TW.po
images/1_config_knowledge.jpeg
images/knowledge-hover.png
images/knowledge.png
openerp_knowledge.egg-info/PKG-INFO
openerp_knowledge.egg-info/SOURCES.txt
openerp_knowledge.egg-info/dependency_links.txt
openerp_knowledge.egg-info/requires.txt
openerp_knowledge.egg-info/top_level.txt
security/ir.model.access.csv
security/knowledge_security.xml
static/src/img/icon.png